setup.py
distributions_chain_udacity/Binomialdistribution.py
distributions_chain_udacity/Gaussiandistribution.py
distributions_chain_udacity/Generaldistribution.py
distributions_chain_udacity/__init__.py
distributions_chain_udacity.egg-info/PKG-INFO
distributions_chain_udacity.egg-info/SOURCES.txt
distributions_chain_udacity.egg-info/dependency_links.txt
distributions_chain_udacity.egg-info/not-zip-safe
distributions_chain_udacity.egg-info/top_level.txt