Metadata-Version: 1.0
Name: distributions-chain-udacity
Version: 0.2
Summary: Gaussian and Binomial distributions
Home-page: UNKNOWN
Author: Eduardo Chain
Author-email: eduardo.d.chain@gmail.com
License: UNKNOWN
Platform: UNKNOWN
